dynaspark/__init__.py
dynaspark/dynaspark.py
dynaspark-1.2.2.3.dist-info/licenses/LICENSE
dynaspark-1.2.2.3.dist-info/METADATA
dynaspark-1.2.2.3.dist-info/WHEEL
dynaspark-1.2.2.3.dist-info/top_level.txt
dynaspark-1.2.2.3.dist-info/RECORD
