Metadata-Version: 2.4
Name: dynaspark
Version: 1.2.2.3
Summary: A Python client for the DynaSpark API - Free AI text generation, text-to-speech, and image generation
Home-page: https://github.com/Th3-C0der/DynaSpark
Author: Th3-C0der
Author-email: dvp.ai.ml@gmail.com
License: MIT
Project-URL: Bug Tracker, https://github.com/Th3-C0der/DynaSpark/issues
Project-URL: Documentation, https://github.com/Th3-C0der/DynaSpark#readme
Project-URL: Source Code, https://github.com/Th3-C0der/DynaSpark
Keywords: ai,text-generation,image-generation,audio-generation,api,dynaspark
Classifier: Development Status :: 4 - Beta
Classifier: Intended Audience :: Developers
Classifier: License :: OSI Approved :: MIT License
Classifier: Operating System :: OS Independent
Classifier: Programming Language :: Python :: 3
Classifier: Programming Language :: Python :: 3.6
Classifier: Programming Language :: Python :: 3.7
Classifier: Programming Language :: Python :: 3.8
Classifier: Programming Language :: Python :: 3.9
Classifier: Programming Language :: Python :: 3.10
Classifier: Programming Language :: Python :: 3.11
Classifier: Programming Language :: Python :: 3.12
Classifier: Topic :: Software Development :: Libraries :: Python Modules
Classifier: Topic :: Scientific/Engineering :: Artificial Intelligence
Requires-Python: >=3.6
License-File: LICENSE
Requires-Dist: requests>=2.30.0
Requires-Dist: urllib3>=2.0.0
Dynamic: author
Dynamic: author-email
Dynamic: classifier
Dynamic: description
Dynamic: description-content-type
Dynamic: home-page
Dynamic: keywords
Dynamic: license
Dynamic: license-file
Dynamic: project-url
Dynamic: requires-dist
Dynamic: requires-python
Dynamic: summary
